cmsplugin_slick/__init__.py
cmsplugin_slick/cms_plugins.py
cmsplugin_slick/models.py
cmsplugin_slick/locale/ru/LC_MESSAGES/django.mo
cmsplugin_slick/locale/ru/LC_MESSAGES/django.po
cmsplugin_slick/locale/ru/LC_MESSAGES/django.po~
cmsplugin_slick/migrations/0001_initial.py
cmsplugin_slick/migrations/0002_carousel_default_style.py
cmsplugin_slick/migrations/0003_auto_20170429_0008.py
cmsplugin_slick/migrations/0004_auto_20170429_0124.py
cmsplugin_slick/migrations/0005_carousel_height.py
cmsplugin_slick/migrations/__init__.py
cmsplugin_slick/static/cmsplugin_slick/ajax-loader.gif
cmsplugin_slick/static/cmsplugin_slick/slick-theme.css
cmsplugin_slick/static/cmsplugin_slick/slick.css
cmsplugin_slick/static/cmsplugin_slick/slick.js
cmsplugin_slick/static/cmsplugin_slick/fonts/slick.eot
cmsplugin_slick/static/cmsplugin_slick/fonts/slick.svg
cmsplugin_slick/static/cmsplugin_slick/fonts/slick.ttf
cmsplugin_slick/static/cmsplugin_slick/fonts/slick.woff
cmsplugin_slick/templates/cmsplugin_slick/carousel.djhtml
cmsplugin_slick/templates/cmsplugin_slick/carousel.djhtml~
cmsplugin_slick/templates/cmsplugin_slick/element_wrapper.djhtml
cmsplugin_slick/templates/cmsplugin_slick/element_wrapper.djhtml~
cmsplugin_slick/templates/cmsplugin_slick/folder_carousel.djhtml
cmsplugin_slick/templates/cmsplugin_slick/folder_carousel.djhtml~
cmsplugin_slick-0.2.4.dist-info/DESCRIPTION.rst
cmsplugin_slick-0.2.4.dist-info/METADATA
cmsplugin_slick-0.2.4.dist-info/RECORD
cmsplugin_slick-0.2.4.dist-info/WHEEL
cmsplugin_slick-0.2.4.dist-info/metadata.json
cmsplugin_slick-0.2.4.dist-info/top_level.txt
