Metadata-Version: 2.0
Name: cmsplugin-slick
Version: 0.2.4
Summary: Django-CMS plugin for slick carousel
Home-page: https://github.com/paramono/cmsplugin-slick
Author: Alexander Paramonov
Author-email: alex@paramono.com
License: GPLv3+
Keywords: Django CMS slick slider plugin
Platform: UNKNOWN
Classifier: Development Status :: 3 - Alpha
Classifier: Intended Audience :: Developers
Classifier: Natural Language :: English
Classifier: Programming Language :: Python :: 3
Classifier: Programming Language :: Python :: 3.3
Classifier: Programming Language :: Python :: 3.4
Classifier: Programming Language :: Python :: 3.5
Requires-Dist: Django (>=1.9)
Requires-Dist: django-cms (>=3)
Requires-Dist: django-filer
